<loadFolders>
	<v1.4>
		<li>/</li>
		<li>1.4</li>
		<li IfModActive="sarg.alphabiomes">1.4/Mods/AlphaBiomes</li>
		<li IfModActive="sarg.alphaanimals">1.4/Mods/AlphaAnimals</li>
		<li IfModActive="Ludeon.RimWorld.Royalty">1.4/Mods/Royalty</li>
		<li IfModActive="OskarPotocki.VFE.Insectoid">1.4/Mods/VanillaInsectoidsExpanded</li>
		<li IfModActive="vanillaracesexpanded.phytokin">1.4/Mods/VanillaRacesExpandedPhytokin</li>
		<li IfModActive="vanillaracesexpanded.sanguophage">1.4/Mods/VanillaRacesExpandedSanguophage</li>
		<li IfModActive="vanillaracesexpanded.android">1.4/Mods/VanillaRacesExpandedAndroid</li>
		<li IfModActive="DankPyon.Medieval.Overhaul">1.4/Mods/MedievalOverhaul</li>
		<li IfModActive="vanillaracesexpanded.fungoid">1.4/Mods/VanillaRacesExpandedFungoid</li>
	</v1.4>
	
	<v1.5>
		<li>/</li>
		<li>1.5</li>
		<li IfModActive="sarg.alphabiomes">1.5/Mods/AlphaBiomes</li>
		<li IfModActive="sarg.alphaanimals">1.5/Mods/AlphaAnimals</li>
		<li IfModActive="Ludeon.RimWorld.Royalty">1.5/Mods/Royalty</li>
		<li IfModActive="OskarPotocki.VFE.Insectoid">1.5/Mods/VanillaInsectoidsExpanded</li>
		<li IfModActive="vanillaracesexpanded.phytokin">1.5/Mods/VanillaRacesExpandedPhytokin</li>
		<li IfModActive="vanillaracesexpanded.sanguophage">1.5/Mods/VanillaRacesExpandedSanguophage</li>
		<li IfModActive="vanillaracesexpanded.android">1.5/Mods/VanillaRacesExpandedAndroid</li>
		<li IfModActive="DankPyon.Medieval.Overhaul">1.5/Mods/MedievalOverhaul</li>
		<li IfModActive="vanillaracesexpanded.fungoid">1.5/Mods/VanillaRacesExpandedFungoid</li>
	</v1.5>
</loadFolders>


