<?xml version="1.0" encoding="utf-8" ?>
<Defs>
	<AbilityDef Abstract="True" Name="AG_NoTargetAbilities">
		<jobDef>CastAbilityOnThing</jobDef>
		<targetRequired>False</targetRequired>
		<canUseAoeToGetTargets>False</canUseAoeToGetTargets>
		<stunTargetWhileCasting>True</stunTargetWhileCasting>
		<showPsycastEffects>False</showPsycastEffects>
		<displayGizmoWhileUndrafted>true</displayGizmoWhileUndrafted>
		<disableGizmoWhileUndrafted>False</disableGizmoWhileUndrafted>
		<hotKey>Misc12</hotKey>
		<verbProperties>
			<verbClass>Verb_CastAbility</verbClass>
			<warmupTime>0.5</warmupTime>
			<drawAimPie>False</drawAimPie>
			<requireLineOfSight>False</requireLineOfSight>
			<targetParams>
				<canTargetSelf>true</canTargetSelf>
				<canTargetPawns>false</canTargetPawns>
				<canTargetBuildings>false</canTargetBuildings>
				<canTargetAnimals>false</canTargetAnimals>
				<canTargetHumans>false</canTargetHumans>
				<canTargetMechs>false</canTargetMechs>
			</targetParams>
		</verbProperties>
	</AbilityDef>
	<AbilityDef>
		<defName>AG_WingPoweredJump</defName>
		<label>wing-powered jump</label>
		<description>Flap wings to jump a short distance.</description>
		<iconPath>UI/Abilities/AG_WingPoweredJump</iconPath>
		<cooldownTicksRange>2400</cooldownTicksRange>
		<verbProperties>
			<verbClass>Verb_CastAbilityJump</verbClass>
			<label>flap wings</label>
			<violent>false</violent>
			<forceNormalTimeSpeed>false</forceNormalTimeSpeed>
			<warmupTime>0.5</warmupTime>
			<range>6.9</range>
			<requireLineOfSight>true</requireLineOfSight>
			<soundCast>AG_WingsFlapping</soundCast>
			<soundLanding>Longjump_Land</soundLanding>
			<flyWithCarriedThing>true</flyWithCarriedThing>
			<targetParams>
				<canTargetLocations>true</canTargetLocations>
				<canTargetPawns>false</canTargetPawns>
				<canTargetBuildings>false</canTargetBuildings>
			</targetParams>
		</verbProperties>
	</AbilityDef>
	<AbilityDef ParentName="AG_NoTargetAbilities">
		<defName>AG_UnstableMutation</defName>
		<label>unstable mutation</label>
		<description>Forces an unstable mutation on the caster's body. This mutation will activate a new random gene for 12 hours. After that period passes, the gene will deactivate.</description>
		<iconPath>UI/Icons/Genes/AG_UnstableMutation</iconPath>
		<cooldownTicksRange>60000</cooldownTicksRange>
		<comps>
			<li Class="AlphaGenes.CompProperties_GiveHediff">
				<hediffDef>AG_UnstableMutation</hediffDef>
			</li>
		</comps>
	</AbilityDef>
	<AbilityDef ParentName="AG_NoTargetAbilities">
		<defName>AG_ReactiveArmourA</defName>
		<label>reactive armour</label>
		<abilityClass>AlphaGenes.Ability_ReactiveArmour</abilityClass>
		<description>Consumes minerals to harden the users body against piercing and sharp attacks.</description>
		<iconPath>UI/Icons/Genes/AG_ReactiveArmour</iconPath>
		<cooldownTicksRange>300</cooldownTicksRange>
		<displayGizmoWhileUndrafted>false</displayGizmoWhileUndrafted>
	</AbilityDef>
	<AbilityDef ParentName="AG_NoTargetAbilities">
		<defName>AG_MineralOverdriveA</defName>
		<label>mineral overdrive</label>
		<abilityClass>AlphaGenes.Ability_MineralOverdrive</abilityClass>
		<description>Drains minerals to increase the work effiency of the user.</description>
		<iconPath>UI/Icons/Genes/AG_MineralOverdrive</iconPath>
		<cooldownTicksRange>60000</cooldownTicksRange>
		<displayGizmoWhileUndrafted>true</displayGizmoWhileUndrafted>
	</AbilityDef>
	<AbilityDef>
		<defName>AG_MineralShock</defName>
		<label>mineral shock</label>
		<description>Use the stored minerals to shoot a concentrated lump of soil. This will cause blunt trauma in the target.</description>
		<iconPath>UI/Icons/Genes/AG_MineralShock</iconPath>
		<cooldownTicksRange>60</cooldownTicksRange>
		<aiCanUse>true</aiCanUse>
		<verbProperties>
			<verbClass>Verb_CastAbility</verbClass>
			<range>5.9</range>
			<warmupTime>0.5</warmupTime>
			<soundCast>AG_Rocks</soundCast>
		</verbProperties>
		<comps>
			<li Class="AlphaGenes.CompProperties_AbilityMineralCost">
				<mineralCost>0.1</mineralCost>
			</li>
			<li Class="CompProperties_AbilityLaunchProjectile">
				<projectileDef>AG_Rocks</projectileDef>
			</li>
		</comps>
	</AbilityDef>
	<AbilityDef>
		<defName>AG_Zap</defName>
		<label>electric discharge</label>
		<description>Accumulate energy and release it in a powerful electric jolt that electrocutes its target..</description>
		<iconPath>UI/Icons/Genes/AG_Zap</iconPath>
		<cooldownTicksRange>15000</cooldownTicksRange>
		<displayOrder>200</displayOrder>
		<aiCanUse>true</aiCanUse>
		<verbProperties>
			<verbClass>Verb_CastAbility</verbClass>
			<range>7.9</range>
			<warmupTime>0.5</warmupTime>
			<soundCast>AG_Lightning</soundCast>
		</verbProperties>
		<comps>
			<li Class="CompProperties_AbilityLaunchProjectile">
				<projectileDef>AG_Lightning</projectileDef>
			</li>
		</comps>
	</AbilityDef>
	<AbilityDef>
		<defName>AG_GreaterFireSpew</defName>
		<label>greater fire spew</label>
		<description>Spew flammable bile generated by a special organ in the neck. The bile ignites immediately in contact with oxygen, creating a dangerous conflagration that will set everything on its path on fire.</description>
		<iconPath>UI/Icons/Genes/AG_GreaterFireSpew</iconPath>
		<cooldownTicksRange>300000</cooldownTicksRange>
		<aiCanUse>true</aiCanUse>
		<warmupStartSound>FireSpew_Warmup</warmupStartSound>
		<verbProperties>
			<verbClass>Verb_CastAbility</verbClass>
			<range>10.9</range>
			<warmupTime>1</warmupTime>
			<soundCast>FireSpew_Resolve</soundCast>
			<targetParams>
				<canTargetLocations>true</canTargetLocations>
			</targetParams>
		</verbProperties>
		<comps>
			<li Class="CompProperties_AbilityLaunchProjectile">
				<projectileDef>AG_GreaterFireSpew</projectileDef>
			</li>
		</comps>
	</AbilityDef>
</Defs>